gowershell/__init__.py
gowershell/core.py
gowershell/gowershell.exe
gowershell-0.1.1.dist-info/licenses/LICENSE
gowershell-0.1.1.dist-info/METADATA
gowershell-0.1.1.dist-info/WHEEL
gowershell-0.1.1.dist-info/top_level.txt
gowershell-0.1.1.dist-info/RECORD
